{
"type": "FeatureCollection",
"name": "HW 2 4326 GeoJSON",
"crs": { "type": "name", "properties": { "name": "urn:ogc:def:crs:OGC:1.3:CRS84" } },
"features": [
{ "type": "Feature", "properties": { "id": 1 }, "geometry": { "type": "Point", "coordinates": [ -72.75147078202032, 41.73636841576058 ] } }
]
}
